{
  "ClassName": "",
  "Chance": 1,
  "Quantity": {
    "Min": 0,
    "Max": 0
  },
  "Health": [],
  "InventoryAttachments": [
    {
      "SlotName": "Headgear",
      "Items": [
        {
          "ClassName": "SantasHat",
          "Chance": 1,
          "Quantity": {
            "Min": 0,
            "Max": 0
          },
          "Health": [
            {
              "Min": 0.7,
              "Max": 1,
              "Zone": ""
            }
          ],
          "InventoryAttachments": [],
          "InventoryCargo": [],
          "ConstructionPartsBuilt": [],
          "Sets": []
        }
      ]
    },
    {
      "SlotName": "Body",
      "Items": [
        {
          "ClassName": "Msp_SantaJacket",
          "Chance": 1,
          "Quantity": {
            "Min": 0,
            "Max": 0
          },
          "Health": [
            {
              "Min": 0.7,
              "Max": 1,
              "Zone": ""
            }
          ],
          "InventoryAttachments": [],
          "InventoryCargo": [],
          "ConstructionPartsBuilt": [],
          "Sets": []
        }
      ]
    },
    {
      "SlotName": "Legs",
      "Items": [
        {
          "ClassName": "Msp_SantaPants",
          "Chance": 1,
          "Quantity": {
            "Min": 0,
            "Max": 0
          },
          "Health": [
            {
              "Min": 0.7,
              "Max": 1,
              "Zone": ""
            }
          ],
          "InventoryAttachments": [],
          "InventoryCargo": [],
          "ConstructionPartsBuilt": [],
          "Sets": []
        }
      ]
    },
    {
      "SlotName": "Feet",
      "Items": [
        {
          "ClassName": "MilitaryBoots_Black",
          "Chance": 1,
          "Quantity": {
            "Min": 0,
            "Max": 0
          },
          "Health": [
            {
              "Min": 0.7,
              "Max": 1,
              "Zone": ""
            }
          ],
          "InventoryAttachments": [],
          "InventoryCargo": [],
          "ConstructionPartsBuilt": [],
          "Sets": []
        }
      ]
    },
    {
      "SlotName": "Mask",
      "Items": [
        {
          "ClassName": "SantasBeard",
          "Chance": 1,
          "Quantity": {
            "Min": 0,
            "Max": 0
          },
          "Health": [
            {
              "Min": 0.7,
              "Max": 1,
              "Zone": ""
            }
          ],
          "InventoryAttachments": [],
          "InventoryCargo": [],
          "ConstructionPartsBuilt": [],
          "Sets": []
        }
      ]
    },
    {
      "SlotName": "Hands",
      "Items": [
        {
          "ClassName": "SFP_RK62",
          "Chance": 1,
          "Quantity": {
            "Min": 0,
            "Max": 0
          },
          "Health": [
            {
              "Min": 0.7,
              "Max": 1,
              "Zone": ""
            }
          ],
          "InventoryAttachments": [
            {
              "SlotName": "",
              "Items": [
                {
                  "ClassName": "SFP_Mag_RK62_30rnd",
                  "Chance": 1,
                  "Quantity": {
                    "Min": 0,
                    "Max": 0
                  },
                  "Health": [
                    {
                      "Min": 0.7,
                      "Max": 1,
                      "Zone": ""
                    }
                  ],
                  "InventoryAttachments": [],
                  "InventoryCargo": [],
                  "ConstructionPartsBuilt": [],
                  "Sets": []
                }
              ]
            }
          ],
          "InventoryCargo": [],
          "ConstructionPartsBuilt": [],
          "Sets": []
        }
      ]
    },
    {
      "SlotName": "Eyes",
      "Items": [
        {
          "ClassName": "AviatorGlasses",
          "Chance": 1,
          "Quantity": {
            "Min": 0,
            "Max": 0
          },
          "Health": [
            {
              "Min": 0.7,
              "Max": 1,
              "Zone": ""
            }
          ],
          "InventoryAttachments": [],
          "InventoryCargo": [],
          "ConstructionPartsBuilt": [],
          "Sets": []
        }
      ]
    }
  ],
  "InventoryCargo": [
    {
      "ClassName": "SFP_Mag_RK62_30rnd",
      "Chance": 1,
      "Quantity": {
        "Min": 0,
        "Max": 0
      },
      "Health": [],
      "InventoryAttachments": [],
      "InventoryCargo": [],
      "ConstructionPartsBuilt": [],
      "Sets": []
    },
    {
      "ClassName": "SFP_Mag_RK62_30rnd",
      "Chance": 1,
      "Quantity": {
        "Min": 0,
        "Max": 0
      },
      "Health": [],
      "InventoryAttachments": [],
      "InventoryCargo": [],
      "ConstructionPartsBuilt": [],
      "Sets": []
    },
    {
      "ClassName": "SFP_Mag_RK62_30rnd",
      "Chance": 1,
      "Quantity": {
        "Min": 0,
        "Max": 0
      },
      "Health": [],
      "InventoryAttachments": [],
      "InventoryCargo": [],
      "ConstructionPartsBuilt": [],
      "Sets": []
    },
    {
      "ClassName": "SFP_Mag_RK62_30rnd",
      "Chance": 1,
      "Quantity": {
        "Min": 0,
        "Max": 0
      },
      "Health": [],
      "InventoryAttachments": [],
      "InventoryCargo": [],
      "ConstructionPartsBuilt": [],
      "Sets": []
    },
    {
      "ClassName": "SFP_Mag_RK62_30rnd",
      "Chance": 1,
      "Quantity": {
        "Min": 0,
        "Max": 0
      },
      "Health": [],
      "InventoryAttachments": [],
      "InventoryCargo": [],
      "ConstructionPartsBuilt": [],
      "Sets": []
    },
    {
      "ClassName": "SFP_Mag_RK62_30rnd",
      "Chance": 1,
      "Quantity": {
        "Min": 0,
        "Max": 0
      },
      "Health": [],
      "InventoryAttachments": [],
      "InventoryCargo": [],
      "ConstructionPartsBuilt": [],
      "Sets": []
    },
    {
      "ClassName": "SFP_Mag_RK62_30rnd",
      "Chance": 1,
      "Quantity": {
        "Min": 0,
        "Max": 0
      },
      "Health": [],
      "InventoryAttachments": [],
      "InventoryCargo": [],
      "ConstructionPartsBuilt": [],
      "Sets": []
    },
    {
      "ClassName": "SFP_Mag_RK62_30rnd",
      "Chance": 1,
      "Quantity": {
        "Min": 0,
        "Max": 0
      },
      "Health": [],
      "InventoryAttachments": [],
      "InventoryCargo": [],
      "ConstructionPartsBuilt": [],
      "Sets": []
    }
  ],
  "ConstructionPartsBuilt": [],
  "Sets": []
}