{
    "m_Version": 6,
    "m_DisplayName": "Krasnostav Trading Zone",
    "Position": [
        11924.7001953125,
        140.6999969482422,
        12527.0
    ],
    "Radius": 1000.0,
    "BuyPricePercent": 100.0,
    "SellPricePercent": -1.0,
    "Stock": {
        "rffsheli_apache_driverdoor_desert": 0,
        "ext_uh1y": 1,
        "rffsheli_mi2_driverdoor": 0,
        "civsedandoors_driver_black": 75,
        "rffsheli_bo105m_cargo4_blackcamo": 0,
        "expansionmh6": 0,
        "hatchbackdoors_driver_white": 75,
        "hatchback_02_door_2_1_blue": 75,
        "rffsheli_ka26_cargo1": 0,
        "rffsheli_ka26_cargo2": 0,
        "rffsheli_r22_driverdoor": 1,
        "sparkplug": 1,
        "expansiontractorfrontwheel": 75,
        "truck_01_door_1_1": 75,
        "civsedandoors_driver": 75,
        "rffsheli_bell429_medic": 0,
        "ext_ka52": 0,
        "cj_milbattery_tan": 0,
        "ext_ah64d": 0,
        "rffsheli_bo105m_codriverdoor": 0,
        "rffsheli_hydraulic_hoses": 1,
        "civsedandoors_codriver_black": 75,
        "rffsheli_blackhawk_budhawk": 0,
        "rffsheli_mi2_cargo1": 0,
        "expansionkeychain_orange": 75,
        "rffsheli_bell429_codriverdoor_medic": 0,
        "hatchbackdoors_driver": 75,
        "rffsheli_bell429_interior_medic": 0,
        "ext_ka60": 0,
        "rffsheli_bell429_codriverdoor_police": 0,
        "expansion_landrover_left": 75,
        "expansionkeychain_pink": 75,
        "rffsheli_bell429_cargo4_police": 0,
        "ext_ka52_door_2_1": 0,
        "expansiontractordoorscodriver": 75,
        "rffsheli_blackhawk_cargo1a": 1,
        "rffsheli_r22_codriverdoor": 1,
        "rffsheli_bell429_codriverdoor_zs": 0,
        "rffsheli_blackhawk_cargo2_blackblackhawk": 0,
        "rffsheli_bell429_cargo4_zs": 0,
        "rffsheli_mi2_military": 0,
        "offroad_02_door_2_1": 75,
        "offroad_02_door_2_2": 75,
        "expansion_landrover_trunk": 75,
        "truck_01_door_2_1": 75,
        "sedan_02_door_2_2_red": 75,
        "rffsheli_ec135_cargo3_blackcamo": 0,
        "rffsheli_igniter_plug": 1,
        "rffsheli_blackhawk_cargo2a": 1,
        "rffsheli_bell429_driverdoor_zs": 0,
        "rffsheli_bell429_rearseats_zs": 0,
        "civsedandoors_backleft": 75,
        "rffsheli_r22_black": 0,
        "sedan_02_trunk_grey": 75,
        "rffsheli_bell429_rearseats_police": 0,
        "rffsheli_ec135": 0,
        "rffsheli_littlebird_desert": 0,
        "hatchbacktrunk_blue": 75,
        "rffsheli_blackhawk_codriverdoor": 1,
        "rffsheli_bell429_cargo1_zs": 0,
        "cj_battery9v_1": 0,
        "rffsheli_blackhawk_cargo4_woodland": 0,
        "rffsheli_blackhawk_driverdoor_blackblackhawk": 0,
        "truck_01_door_2_1_blue": 75,
        "hatchbacktrunk": 75,
        "rffsheli_bell429_police": 0,
        "cj_battery9v_4": 0,
        "expansiontractordoorsdriver": 75,
        "rffsheli_bell429_cargo1": 0,
        "rffsheli_bell429_cargo2": 0,
        "rffsheli_bell429_cargo3": 0,
        "expansionuh1h": 0,
        "expansionkeychain_grey": 75,
        "ext_ka60_backwheel": 0,
        "ext_uh60m_door_2_1": 0,
        "ext_uh60m_door_2_2": 0,
        "expansiontractorbackwheel": 75,
        "rffsheli_bo105m_cargo2": 0,
        "rffsheli_bo105m_cargo3": 0,
        "rffsheli_bo105m_cargo4": 0,
        "rffsheli_blackhawk_cargo2a_budhawk": 0,
        "civsedanwheel": 75,
        "civsedantrunk": 75,
        "ext_uh60m": 0,
        "hatchback_02_trunk_black": 75,
        "truck_01_door_2_1_orange": 75,
        "rffsheli_bell429_interior": 0,
        "rffsheli_bo105m_fuselage": 0,
        "sedan_02_door_1_1_grey": 75,
        "rffsheli_bo105m_cargo1_blackcamo": 0,
        "camonet": 186,
        "offroad_02_hood": 75,
        "carradiator": 0,
        "rffsheli_bell429_cargo1_medic": 0,
        "ext_aw159_backwheel": 0,
        "rffsheli_blackhawk_cargo2a_blackblackhawk": 0,
        "rffsheli_apache": 0,
        "ext_mi24_wheel_2_1": 0,
        "ext_mi24_wheel_2_2": 0,
        "ext_uh1y_door_2_1": 1,
        "rffsheli_blackhawk_codriverdoor_budhawk": 0,
        "rffsheli_blackhawk_cargo1_woodland": 0,
        "expansiongyrocopter": 1,
        "rffsheli_apache_driverdoor": 0,
        "rffsheli_r22": 1,
        "civsedandoors_backright": 75,
        "expansion_mh6_door_2_1_black": 75,
        "truckbattery": 0,
        "hatchback_02_door_2_1": 75,
        "hatchback_02_door_2_2": 75,
        "ext_merlinhc3_backwheel": 0,
        "rffsheli_apache_desert": 0,
        "rffsheli_blackhawk_cargo4_blackblackhawk": 0,
        "hatchback_02_door_2_1_black": 75,
        "expansionuazdoorcargo2": 75,
        "sedan_02_trunk_red": 75,
        "rffsheli_bo105m_fuselage_blackcamo": 0,
        "civsedandoors_driver_wine": 75,
        "ext_mi171": 0,
        "civsedanhood_wine": 75,
        "expansionmerlinbackwheel": 75,
        "rffsheli_blackhawk_cargo3_budhawk": 0,
        "ext_ka52backwheel": 0,
        "rffsheli_flight_case_blue": 1,
        "hatchbackdoors_codriver_white": 75,
        "ext_mi8_attack": 0,
        "rffsheli_blackhawk_cargo2a_woodland": 0,
        "rffsheli_ec135_driverdoor_blackcamo": 0,
        "rffsheli_bo105m_cargo2_blackcamo": 0,
        "rffsheli_bo105m": 0,
        "sedan_02_hood": 75,
        "expansion_mh6_door_1_2_black": 75,
        "expansionbuswheel": 75,
        "rffsheli_blackhawk_cargo1a_woodland": 0,
        "rffsheli_bell429_driverdoor": 0,
        "ext_aw159_frontwheel": 0,
        "expansion_landrover_driverdoor": 75,
        "rffsheli_ch53e": 0,
        "expansion_landrover_wheel": 75,
        "expansionuazwheel": 75,
        "expansionkeychain_blue": 75,
        "civsedanhood_black": 75,
        "expansionvodnikdoordriver": 75,
        "rffsheli_apache_codriverdoor_winter": 0,
        "rffsheli_ec135_cargo4_blackcamo": 0,
        "rffsheli_ka26_codriverdoor": 0,
        "expansion_mh6_door_1_1": 75,
        "expansion_mh6_door_1_2": 75,
        "ext_merlinhc3_door_1_1": 0,
        "hatchback_02_door_1_2_blue": 75,
        "hatchback_02_hood_blue": 75,
        "civsedandoors_backleft_wine": 75,
        "truck_01_hood": 75,
        "expansionkeychain_black": 75,
        "rffsheli_bo105m_codriverdoor_blackcamo": 0,
        "ext_merlinhc3_cargo_door": 0,
        "cj_milbattery_black": 0,
        "sedan_02_hood_red": 75,
        "expansioncarkey": 0,
        "headlighth7_box": 0,
        "rffsheli_bell429_cargo2_medic": 0,
        "expansionhelicopterbattery": 1,
        "rffsheli_wiring_harness": 1,
        "rffsheli_blackhawk_blackblackhawk": 0,
        "ext_mi24_door_1_1": 0,
        "rffsheli_apache_codriverdoor": 0,
        "rffsheli_ec135_cargo1": 0,
        "rffsheli_ec135_cargo2": 0,
        "rffsheli_ec135_cargo3": 0,
        "ext_merlinhc3_frontwheel": 0,
        "ext_mi24_door_1_2": 0,
        "civsedanhood": 75,
        "rffsheli_blackhawk_cargo1_blackblackhawk": 0,
        "expansion_mh6_door_2_2_black": 75,
        "hatchback_02_trunk": 75,
        "rffsheli_ec135_cargo4": 0,
        "rffsheli_ec135_codriverdoor_blackcamo": 0,
        "rffsheli_r22_codriverdoor_black": 0,
        "ext_ch_47f": 0,
        "hatchback_02_door_2_2_black": 75,
        "rffsheli_bell429_codriverdoor": 0,
        "rffsheli_ec135_cargo1_blackcamo": 0,
        "rffsheli_ec135_cargo2_blackcamo": 0,
        "rffsheli_r22_red": 0,
        "canistergasoline": 0,
        "hatchbackwheel": 100,
        "expansion_landrover_right": 75,
        "expansionuazdoorcodriver": 75,
        "ext_mi8": 0,
        "expansionmerlinfrontwheel": 75,
        "sedan_02_door_1_1": 75,
        "sedan_02_door_1_2": 75,
        "mc_battery9v": 0,
        "civsedandoors_backright_wine": 75,
        "ext_tac_radio": 1,
        "rffsheli_blackhawk_cargo3_woodland": 0,
        "ext_mi24": 0,
        "sedan_02_hood_grey": 75,
        "rffsheli_r22_driverdoor_red": 0,
        "rffsheli_blackhawk_cargo4_budhawk": 0,
        "ext_ah1z_door_1_1": 0,
        "ext_mi24_door_cargo_2": 0,
        "hatchback_02_trunk_blue": 75,
        "expansionkeychain_yellow": 75,
        "truck_01_wheeldouble": 75,
        "rffsheli_littlebird": 0,
        "expansion_mh6_door_1_1_black": 75,
        "headlighth7": 1,
        "rffsheli_blackhawk_driverdoor_woodland": 0,
        "expansionuazdoordriver": 75,
        "hatchback_02_hood": 75,
        "sedan_02_door_1_1_red": 75,
        "rffsheli_blackhawk_cargo1a_budhawk": 0,
        "hatchback_02_door_1_1_black": 75,
        "rffsheli_ka26": 0,
        "rffsheli_mi2": 0,
        "expansionkeychain_green": 75,
        "carbattery": 0,
        "rffsheli_ch53e_cargo1": 0,
        "rffsheli_ch53e_cargo2": 0,
        "truck_01_door_1_1_orange": 75,
        "rffsheli_mi2_driverdoor_hornet": 0,
        "hatchbackdoors_codriver": 75,
        "rffsheli_apache_driverdoor_winter": 0,
        "rffsheli_r22_driverdoor_black": 0,
        "rffsheli_bell429_rearseats": 0,
        "offroad_02_trunk": 75,
        "tirerepairkit": 75,
        "rffsheli_ec135_codriverdoor": 0,
        "rffsheli_bo105m_driverdoor": 0,
        "rffsheli_bell429_cargo3_zs": 0,
        "rffsheli_mi2_codriverdoor": 0,
        "ext_ka52frontwheel": 0,
        "rffsheli_bo105m_blackcamo": 0,
        "expansionbuswheeldouble": 75,
        "civsedandoors_codriver_wine": 75,
        "rffsheli_bell429_cargo4": 0,
        "expansionkeychain_purp": 75,
        "ext_ah1z": 0,
        "rffsheli_blackhawk_driverdoor_budhawk": 0,
        "rffsheli_bell429_cargo3_medic": 0,
        "civsedantrunk_wine": 75,
        "rffsheli_ch47_cargo1": 0,
        "rffsheli_ch47_cargo2": 0,
        "rffsheli_bell429_driverdoor_police": 0,
        "rffsheli_bo105m_cargo3_blackcamo": 0,
        "ext_uh60m_door_1_2": 0,
        "expansionuazdoorcargo1": 75,
        "hatchbackdoors_codriver_blue": 75,
        "rffsheli_bo105m_cargo1": 0,
        "cj_sparkplug_box_1": 0,
        "cj_sparkplug_box_2": 0,
        "sedan_02_door_2_1_grey": 75,
        "battery9v": 0,
        "expansionigniterplug": 1,
        "rffsheli_blackhawk_cargo3_blackblackhawk": 0,
        "hatchback_02_door_2_2_blue": 75,
        "cj_battery9v_2": 0,
        "cj_battery9v_3": 0,
        "glowplug": 0,
        "truck_01_wheel": 75,
        "ext_mi8backwheel": 0,
        "ext_merlinhc3": 0,
        "rffsheli_mi2_codriverdoor_hornet": 0,
        "rffsheli_apache_winter": 0,
        "hatchbacktrunk_white": 75,
        "sedan_02_door_2_2_grey": 75,
        "rffsheli_blackhawk": 1,
        "sedan_02_wheel": 75,
        "sedan_02_trunk": 75,
        "hatchback_02_door_1_1_blue": 75,
        "rffsheli_ka26_driverdoor": 0,
        "rffsheli_bell429_interior_police": 0,
        "rffsheli_bell429_interior_zs": 0,
        "ext_ka52_door_1_1": 0,
        "civsedandoors_backleft_black": 75,
        "rffsheli_bell429_skids": 0,
        "civsedandoors_backright_black": 75,
        "rffsheli_bell429_skids_zs": 0,
        "ext_ka60_frontwheel": 0,
        "rffsheli_blackhawk_woodland": 0,
        "rffsheli_bell429_skids_police": 0,
        "offroad_02_door_1_1": 75,
        "offroad_02_door_1_2": 75,
        "rffsheli_aviation_battery": 1,
        "expansion_mh6_door_2_1": 75,
        "expansion_mh6_door_2_2": 75,
        "ext_merlinhc3_door_2_1": 0,
        "rffsheli_apache_codriverdoor_desert": 0,
        "sedan_02_door_2_1_red": 75,
        "hatchback_02_door_1_2_black": 75,
        "expansionhydraulichoses": 1,
        "civsedandoors_codriver": 75,
        "rffsheli_blackhawk_cargo1a_blackblackhawk": 0,
        "rffsheli_r22_codriverdoor_red": 0,
        "hatchbackhood_white": 75,
        "rffsheli_bo105m_driverdoor_blackcamo": 0,
        "rffsheli_ec135_blackcamo": 0,
        "ext_mi24_door_2_1": 0,
        "ext_mi24_door_2_2": 0,
        "hatchback_02_wheel": 75,
        "ext_ka60_door": 0,
        "expansionvodnikwheel": 75,
        "rffsheli_bell429_cargo3_police": 0,
        "expansion_landrover_hood": 75,
        "truck_01_hood_orange": 75,
        "sedan_02_door_1_2_red": 75,
        "hatchback_02_hood_black": 75,
        "rffsheli_bell429_rearseats_medic": 0,
        "expansionkeychain_white": 75,
        "ext_ah1z_door_2_1": 0,
        "hatchbackhood_blue": 75,
        "wrench": 1,
        "ext_mh6": 0,
        "rffsheli_littlebird_camo": 0,
        "rffsheli_blackhawk_driverdoor": 1,
        "cj_milbattery_green": 0,
        "rffsheli_bell429_cargo4_medic": 0,
        "rffsheli_blackhawk_cargo": 0,
        "rffsheli_blackhawk_cargo1": 1,
        "rffsheli_blackhawk_cargo2": 1,
        "rffsheli_blackhawk_cargo3": 1,
        "rffsheli_blackhawk_cargo4": 1,
        "rffsheli_mi2_driverdoor_military": 0,
        "ext_uh60m_door_1_1": 0,
        "ext_mi8frontwheel": 0,
        "sedan_02_door_2_1": 75,
        "sedan_02_door_2_2": 75,
        "rffsheli_ec135_driverdoor": 0,
        "rffsheli_blackhawk_codriverdoor_blackblackhawk": 0,
        "rffsheli_mi2_cargo1_military": 0,
        "ext_mi8door": 0,
        "expansionuazdoorhood": 75,
        "rffsheli_mi2_cargo1_hornet": 0,
        "rffsheli_blackhawk_cargo1_budhawk": 0,
        "rffsheli_bell429_driverdoor_medic": 0,
        "ext_mi24_wheel_1_1": 0,
        "hatchbackhood": 75,
        "rffsheli_blackhawk_cargo2_budhawk": 0,
        "truck_01_hood_blue": 75,
        "rffsheli_bell429_zs": 0,
        "civsedantrunk_black": 75,
        "expansionvodnikdoorcodriver": 75,
        "expansion_landrover_codriverdoor": 75,
        "ext_uh1y_door_1_1": 1,
        "rffsheli_blackhawk_cargo2_woodland": 0,
        "truck_01_door_1_1_blue": 75,
        "rffsheli_blackhawk_codriverdoor_woodland": 0,
        "rffsheli_mi2_codriverdoor_military": 0,
        "ext_mi24_door_cargo_1": 0,
        "rffsheli_bell429_cargo1_police": 0,
        "offroad_02_wheel": 75,
        "expansionuh1hdoor_1_1": 75,
        "expansionuh1hdoor_1_2": 75,
        "ext_mi24_wheel_1_2": 0,
        "rffsheli_mi2_hornet": 0,
        "hatchbackdoors_driver_blue": 75,
        "expansionmerlin": 0,
        "rffsheli_ch47": 0,
        "rffsheli_bell429_skids_medic": 0,
        "ext_aw159": 0,
        "sedan_02_door_1_2_grey": 75,
        "hatchback_02_door_1_1": 75,
        "hatchback_02_door_1_2": 75,
        "expansionkeychain_red": 75
    }
}